ansys/tools/local_product_launcher/__init__.py
ansys/tools/local_product_launcher/_cli.py
ansys/tools/local_product_launcher/_plugins.py
ansys/tools/local_product_launcher/_vendored/cyberchannel.py
ansys/tools/local_product_launcher/config.py
ansys/tools/local_product_launcher/grpc_transport.py
ansys/tools/local_product_launcher/helpers/__init__.py
ansys/tools/local_product_launcher/helpers/grpc.py
ansys/tools/local_product_launcher/helpers/ports.py
ansys/tools/local_product_launcher/interface.py
ansys/tools/local_product_launcher/launch.py
ansys/tools/local_product_launcher/product_instance.py
ansys/tools/local_product_launcher/py.typed
ansys_tools_local_product_launcher-0.3.0.dist-info/METADATA
ansys_tools_local_product_launcher-0.3.0.dist-info/WHEEL
ansys_tools_local_product_launcher-0.3.0.dist-info/entry_points.txt
ansys_tools_local_product_launcher-0.3.0.dist-info/licenses/AUTHORS
ansys_tools_local_product_launcher-0.3.0.dist-info/licenses/LICENSE
ansys_tools_local_product_launcher-0.3.0.dist-info/RECORD
