Metadata-Version: 2.4
Name: ansys-tools-local-product-launcher
Version: 0.3.0
Summary: A utility for launching Ansys products on a local machine
License: MIT
License-File: AUTHORS
License-File: LICENSE
Author: ANSYS, Inc.
Author-email: pyansys.core@ansys.com
Maintainer: ANSYS, Inc.
Maintainer-email: pyansys.core@ansys.com
Requires-Python: >=3.10,<4.0
Classifier: Development Status :: 5 - Production/Stable
Classifier: License :: OSI Approved :: MIT License
Classifier: Operating System :: OS Independent
Classifier: Programming Language :: Python :: 3
Classifier: Programming Language :: Python :: 3.10
Classifier: Programming Language :: Python :: 3.11
Classifier: Programming Language :: Python :: 3.12
Classifier: Programming Language :: Python :: 3.13
Classifier: Programming Language :: Python :: 3.14
Requires-Dist: ansys-tools-common (>=0.1.0)
Requires-Dist: grpcio (>=1.51.1)
Requires-Dist: grpcio-health-checking (>=1.43)
Project-URL: Repository, https://github.com/ansys/ansys-tools-local-product-launcher
